ocptv/__init__.py
ocptv/api.py
ocptv/formatter.py
ocptv/py.typed
ocptv/output/__init__.py
ocptv/output/config.py
ocptv/output/dut.py
ocptv/output/emit.py
ocptv/output/measurement.py
ocptv/output/objects.py
ocptv/output/run.py
ocptv/output/runtime_checks.py
ocptv/output/source.py
ocptv/output/step.py
ocptv-0.1.7.dist-info/LICENSE
ocptv-0.1.7.dist-info/METADATA
ocptv-0.1.7.dist-info/WHEEL
ocptv-0.1.7.dist-info/top_level.txt
ocptv-0.1.7.dist-info/RECORD
