Metadata-Version: 2.1
Name: ocptv
Version: 0.1.7
Summary: OCP Test & Validation project api
Author-email: OCP Test & Validation <ocp-test-validation@OCP-All.groups.io>
License: MIT License
Project-URL: Homepage, https://github.com/opencomputeproject/ocp-diag-python
Project-URL: Bug reports, https://github.com/opencomputeproject/ocp-diag-python/issues
Project-URL: Source, https://github.com/opencomputeproject/ocp-diag-python
Keywords: ocp,ocptv,specification
Classifier: License :: OSI Approved :: MIT License
Classifier: Programming Language :: Python
Classifier: Programming Language :: Python :: 3
Classifier: Programming Language :: Python :: 3.7
Classifier: Programming Language :: Python :: 3.8
Classifier: Programming Language :: Python :: 3.9
Classifier: Programming Language :: Python :: 3.10
Classifier: Programming Language :: Python :: 3.11
Classifier: Topic :: System :: Hardware
Requires-Python: >=3.7
License-File: LICENSE
Provides-Extra: dev
Requires-Dist: black; extra == "dev"
Requires-Dist: bumpver; extra == "dev"
Requires-Dist: isort; extra == "dev"
Requires-Dist: pip-tools; extra == "dev"
Requires-Dist: pytest; extra == "dev"
Requires-Dist: pytest-cov; extra == "dev"
Requires-Dist: mypy; extra == "dev"
